sensory_detector/__init__.py
sensory_detector/models/__init__.py
sensory_detector/models/models.py
sensory_detector/yolo_client/__init__.py
sensory_detector/yolo_client/client.py
sensory_detector/yolo_server/__init__.py
sensory_detector/yolo_server/main.py
sensory_detector/yolo_server/app/__init__.py
sensory_detector/yolo_server/app/appconfig.py
sensory_detector/yolo_server/app/config.py
sensory_detector/yolo_server/app/model_cache.py
sensory_detector/yolo_server/app/model_utils.py
sensory_detector/yolo_server/app/path_utils.py
sensory_detector/yolo_server/detectors/__init__.py
sensory_detector/yolo_server/detectors/clip_wrapper.py
sensory_detector/yolo_server/detectors/detector_interface.py
sensory_detector/yolo_server/detectors/easyocr_wrapper.py
sensory_detector/yolo_server/detectors/tesseract_ocr_wrapper.py
sensory_detector/yolo_server/detectors/yolo_wrapper.py
sensory_detector/yolo_server/detectors/tesseract_wrapper/tesseract_worker.py
sensory_detector/yolo_server/detectors/tesseract_wrapper/tesseract_wrapper.py
sensory_detector/yolo_server/endpoints/__init__.py
sensory_detector/yolo_server/endpoints/embeddings.py
sensory_detector/yolo_server/endpoints/endpoints.py
sensory_detector/yolo_server/endpoints/objects.py
sensory_detector/yolo_server/endpoints/shared_input.py
sensory_detector/yolo_server/endpoints/shared_output.py
sensory_detector/yolo_server/endpoints/texts.py
sensory_detector/yolo_server/endpoints/ws_endpoints.py
sensory_detector/yolo_server/ocr/__init__.py
sensory_detector/yolo_server/ocr/image_processor.py
sensory_detector/yolo_server/video_analizer/__init__.py
sensory_detector/yolo_server/video_analizer/asyncIO.py
sensory_detector/yolo_server/video_analizer/frame_reader.py
sensory_detector/yolo_server/video_analizer/video_processor.py
sensory_detector-0.2.4.dist-info/METADATA
sensory_detector-0.2.4.dist-info/WHEEL
sensory_detector-0.2.4.dist-info/entry_points.txt
sensory_detector-0.2.4.dist-info/top_level.txt
sensory_detector-0.2.4.dist-info/RECORD
