Metadata-Version: 2.4
Name: sensory_detector
Version: 0.2.4
Summary: Async ML service and client for sensory detection
Author-email: "m.chui, v.mitui, n.buchtui" <sensory@sensory.com>
License: MIT License
Keywords: computer-vision,machine-learning,yolo,ocr,embeddings,fastapi,async
Classifier: Development Status :: 4 - Beta
Classifier: Intended Audience :: Developers
Classifier: Intended Audience :: Science/Research
Classifier: Programming Language :: Python :: 3
Classifier: Programming Language :: Python :: 3.10
Classifier: Programming Language :: Python :: 3.11
Classifier: Programming Language :: Python :: 3.12
Classifier: Topic :: Scientific/Engineering :: Artificial Intelligence
Classifier: Topic :: Software Development :: Libraries :: Python Modules
Classifier: Topic :: Internet :: WWW/HTTP :: WSGI :: Application
Requires-Python: >=3.10
Requires-Dist: pydantic>=2.0.0
Requires-Dist: numpy
Provides-Extra: client
Requires-Dist: httpx>=0.25.0; extra == "client"
Provides-Extra: server
Requires-Dist: fastapi>=0.100.0; extra == "server"
Requires-Dist: flask; extra == "server"
Requires-Dist: uvicorn[standard]; extra == "server"
Requires-Dist: ultralytics; extra == "server"
Requires-Dist: opencv-python-headless; extra == "server"
Requires-Dist: psutil; extra == "server"
Requires-Dist: av; extra == "server"
Requires-Dist: torch; extra == "server"
Requires-Dist: python-dotenv; extra == "server"
Requires-Dist: python-multipart; extra == "server"
Requires-Dist: cachetools; extra == "server"
Requires-Dist: open-clip-torch==2.29.0; extra == "server"
Requires-Dist: pydantic-settings; extra == "server"
Requires-Dist: easyocr; extra == "server"
Requires-Dist: gunicorn; extra == "server"
Provides-Extra: all
Requires-Dist: sensory_detector[client]; extra == "all"
Requires-Dist: sensory_detector[server]; extra == "all"
